number_utility.py
sbpyp-0.0.1.dist-info/LICENSE
sbpyp-0.0.1.dist-info/METADATA
sbpyp-0.0.1.dist-info/WHEEL
sbpyp-0.0.1.dist-info/top_level.txt
sbpyp-0.0.1.dist-info/RECORD
